deutschland/ausbildungssuche/__init__.py
deutschland/ausbildungssuche/api/__init__.py
deutschland/ausbildungssuche/api/default_api.py
deutschland/ausbildungssuche/api_client.py
deutschland/ausbildungssuche/apis/__init__.py
deutschland/ausbildungssuche/configuration.py
deutschland/ausbildungssuche/exceptions.py
deutschland/ausbildungssuche/model/__init__.py
deutschland/ausbildungssuche/model/response.py
deutschland/ausbildungssuche/model/response_aggregations.py
deutschland/ausbildungssuche/model/response_aggregations_anbieter.py
deutschland/ausbildungssuche/model/response_aggregations_anbieter100128.py
deutschland/ausbildungssuche/model/response_aggregations_anbieter100960.py
deutschland/ausbildungssuche/model/response_aggregations_anbieter10253.py
deutschland/ausbildungssuche/model/response_aggregations_anbieter102800.py
deutschland/ausbildungssuche/model/response_aggregations_anbieter10461.py
deutschland/ausbildungssuche/model/response_aggregations_anbieter10464.py
deutschland/ausbildungssuche/model/response_aggregations_anbieter10606.py
deutschland/ausbildungssuche/model/response_aggregations_anbieter10613.py
deutschland/ausbildungssuche/model/response_aggregations_anbieter10621.py
deutschland/ausbildungssuche/model/response_aggregations_anbieter10837.py
deutschland/ausbildungssuche/model/response_aggregations_anbieter10865.py
deutschland/ausbildungssuche/model/response_aggregations_anbieter108680.py
deutschland/ausbildungssuche/model/response_aggregations_anbieter11031.py
deutschland/ausbildungssuche/model/response_aggregations_anbieter11051.py
deutschland/ausbildungssuche/model/response_aggregations_anbieter1119.py
deutschland/ausbildungssuche/model/response_aggregations_anbieter11203.py
deutschland/ausbildungssuche/model/response_aggregations_anbieter112919.py
deutschland/ausbildungssuche/model/response_aggregations_anbieter11305.py
deutschland/ausbildungssuche/model/response_aggregations_anbieter114819.py
de_ausbildungssuche-0.1.0.dist-info/WHEEL
de_ausbildungssuche-0.1.0.dist-info/METADATA
de_ausbildungssuche-0.1.0.dist-info/RECORD
